padhana/__init__.py
padhana/analysis/__init__.py
padhana/analysis/analysis.py
padhana/analysis/outline.py
padhana/connectors/__init__.py
padhana/connectors/connectors.py
padhana/core/__init__.py
padhana/core/document.py
padhana/model/__init__.py
padhana/model/model.py
padhana/parsers/__init__.py
padhana/parsers/pdf_miner.py
padhana/stores/__init__.py
padhana/stores/stores.py
padhana-1.0.12.dist-info/LICENSE
padhana-1.0.12.dist-info/METADATA
padhana-1.0.12.dist-info/WHEEL
padhana-1.0.12.dist-info/top_level.txt
padhana-1.0.12.dist-info/RECORD
