Metadata-Version: 2.1
Name: padhana
Version: 1.0.12
Summary: PDF document parsing and analysis
Home-page: https://www.github.com/hohonu/padhana
Author: Philip Dodds
Author-email: philip@hohonu.com
License: UNKNOWN
Platform: UNKNOWN
Requires-Dist: attrs (>=17.4.0)
